MANIFEST.in
README.rst
setup.cfg
setup.py
ckanext/__init__.py
ckanext/composite/__init__.py
ckanext/composite/helpers.py
ckanext/composite/plugin.py
ckanext/composite/presets.json
ckanext/composite/validators.py
ckanext/composite/fanstatic/composite-repeating.js
ckanext/composite/fanstatic/composite.css
ckanext/composite/templates/scheming/display_snippets/composite.html
ckanext/composite/templates/scheming/display_snippets/composite_repeating.html
ckanext/composite/templates/scheming/form_snippets/composite.html
ckanext/composite/templates/scheming/form_snippets/composite_header.html
ckanext/composite/templates/scheming/form_snippets/composite_repeating.html
ckanext/composite/templates/scheming/form_snippets/composite_tag_string_autocomplete.html
ckanext/composite/tests/__init__.py
ckanext/composite/tests/test_plugin.py
ckanext_composite.egg-info/PKG-INFO
ckanext_composite.egg-info/SOURCES.txt
ckanext_composite.egg-info/dependency_links.txt
ckanext_composite.egg-info/entry_points.txt
ckanext_composite.egg-info/pbr.json
ckanext_composite.egg-info/top_level.txt