Metadata-Version: 1.1
Name: ckanext-composite
Version: 0.0.2
Summary: "Structured metadata extension for CKAN"
Home-page: https://github.com/espona/ckanext-composite
Author: Lucia Espona
Author-email: lucia.espona@wsl.ch
License: AGPL
Keywords: CKAN scheming composite
Platform: UNKNOWN
Classifier: Development Status :: 4 - Beta
Classifier: License :: OSI Approved :: GNU Affero General Public License v3 or later (AGPLv3+)
Classifier: Programming Language :: Python :: 2.6
Classifier: Programming Language :: Python :: 2.7
